ia_wumpus/__init__.py
ia_wumpus/agente_reativo_v1.py
ia_wumpus/agente_reativo_v2.py
ia_wumpus/ambiente.py
ia_wumpus/dinamica_agente_ambiente.py
ia_wumpus-0.4.0.dist-info/LICENSE
ia_wumpus-0.4.0.dist-info/METADATA
ia_wumpus-0.4.0.dist-info/WHEEL
ia_wumpus-0.4.0.dist-info/RECORD
