Metadata-Version: 2.1
Name: ia-wumpus
Version: 0.4.0
Summary: Projeto O Mundo do Wumpus - Anbiente para estudo da disciplina de Inteligencia Computacional.
Author: Oseiasdfarias
Author-email: oseias.dfarias@gmail.com
Requires-Python: >=3.8
Classifier: Programming Language :: Python :: 3
Classifier: Programming Language :: Python :: 3.8
Classifier: Programming Language :: Python :: 3.9
Classifier: Programming Language :: Python :: 3.10
Classifier: Programming Language :: Python :: 3.11
Requires-Dist: loguru (>=0.7.0,<0.8.0)
Requires-Dist: matplotlib (>=3.7.2,<4.0.0)
Requires-Dist: numpy (>=1.24.3)
Requires-Dist: pandas (>=2.0.3,<3.0.0)
Requires-Dist: rich (>=13.3.5,<14.0.0)
